gitor/__init__.py
gitor/_set.py
gitor/api.py
gitor/gitrequest.py
gitor/repositories.py
gitor-0.0.3.dist-info/LICENSE
gitor-0.0.3.dist-info/METADATA
gitor-0.0.3.dist-info/WHEEL
gitor-0.0.3.dist-info/top_level.txt
gitor-0.0.3.dist-info/RECORD
