Metadata-Version: 2.1
Name: gitor
Version: 0.0.3
Summary: Github python wrapper, Custom made for getting repositories for your python web server.
Home-page: https://github.com/monnapse/gitor
Author: Monnapse
Author-email: monnapse@gmail.com
Project-URL: Bug Tracker, https://github.com/monnapse/gitor/issues
Classifier: Programming Language :: Python :: 3
Classifier: License :: OSI Approved :: MIT License
Classifier: Operating System :: OS Independent
Requires-Python: >=3.7
License-File: LICENSE
